{
  "DEPLOY": {
    "stageName": "DEPLOY",
    "summary": "[G 阶段 · DEPLOY · 终局归档 + Commit 指引] > Session: `wf-20260430013937.` · 终端: 40 files · +1775/-2727 · net -952 行",
    "keyDecisions": [
      "[G 阶段 · DEPLOY · 终局归档 + Commit 指引] > Session: `wf-20260430013937.` · 终端: 40 files · +1775/-2727 · net -952 行",
      "[Batch 1 · Track-B · `feat(e2e)`: Playwright 基础 + compute smoke] git add package.json pnpm-lock.yaml playwright.config.ts tests/",
      "[Batch 2 · Track-A · `refactor(templates)`: physics-core → experiment-core 底座统一] git add public/templates/_shared/experiment-core.js public/templates/chemistry/ public/templates/physics/",
      "[Batch 3 · Track-A 守护 · `feat(arch-guard)`: arch-audit +check-5] git add scripts/arch-audit.sh",
      "[Batch 4 · Track-C 防复发 · `docs/feat(workflow)`: 路线图 + C-5 + skill + 注册] git add docs/roadmap-g.md docs/architecture-constraints.md .workflow/skills/iframe-rpc-safety.md workflow.config.js"
    ],
    "artifacts": [
      "output\\deploy-output.md"
    ],
    "risks": [],
    "correctionHistory": [],
    "meta": {
      "session": "wf-20260430013937."
    },
    "timestamp": "2026-04-30T02:57:13.583Z"
  },
  "_meta": {
    "requirementFingerprint": "commit deploy 指引 用户 终局归档 阶段"
  }
}