{
  "sessions": {
    "wf-20260422-214612": {
      "lastSeq": 1,
      "filePath": "C:\\workspace\\EGPSpace\\output\\runtime\\events\\wf-20260422-214612.jsonl",
      "updatedAt": "2026-04-22T13:46:13.134Z"
    },
    "wf-20260422-215306": {
      "lastSeq": 9,
      "filePath": "C:\\workspace\\EGPSpace\\output\\runtime\\events\\wf-20260422-215306.jsonl",
      "updatedAt": "2026-04-22T14:07:20.162Z"
    },
    "wf-20260422-235201": {
      "lastSeq": 1,
      "filePath": "c:\\workspace\\EGPSpace\\output\\runtime\\events\\wf-20260422-235201.jsonl",
      "updatedAt": "2026-04-22T15:52:01.767Z"
    },
    "wf-20260423-000434": {
      "lastSeq": 15,
      "filePath": "C:\\workspace\\EGPSpace\\output\\runtime\\events\\wf-20260423-000434.jsonl",
      "updatedAt": "2026-04-22T16:43:05.309Z"
    },
    "wf-20260423-005959": {
      "lastSeq": 1,
      "filePath": "C:\\workspace\\EGPSpace\\output\\runtime\\events\\wf-20260423-005959.jsonl",
      "updatedAt": "2026-04-22T17:00:00.043Z"
    },
    "wf-20260423-011725": {
      "lastSeq": 2,
      "filePath": "C:\\workspace\\EGPSpace\\output\\runtime\\events\\wf-20260423-011725.jsonl",
      "updatedAt": "2026-04-22T17:22:09.433Z"
    },
    "wf-20260423-083120": {
      "lastSeq": 1,
      "filePath": "C:\\workspace\\EGPSpace\\output\\runtime\\events\\wf-20260423-083120.jsonl",
      "updatedAt": "2026-04-23T00:31:20.299Z"
    },
    "wf-20260423-083331": {
      "lastSeq": 2,
      "filePath": "C:\\workspace\\EGPSpace\\output\\runtime\\events\\wf-20260423-083331.jsonl",
      "updatedAt": "2026-04-23T02:24:10.317Z"
    },
    "wf-20260423022901.": {
      "lastSeq": 3,
      "filePath": "C:\\workspace\\EGPSpace\\output\\runtime\\events\\wf-20260423022901..jsonl",
      "updatedAt": "2026-04-23T03:11:54.858Z"
    },
    "wf-20260423-120434": {
      "lastSeq": 6,
      "filePath": "C:\\workspace\\EGPSpace\\output\\runtime\\events\\wf-20260423-120434.jsonl",
      "updatedAt": "2026-04-23T04:18:23.636Z"
    },
    "wf-20260423042819.": {
      "lastSeq": 7,
      "filePath": "C:\\workspace\\EGPSpace\\output\\runtime\\events\\wf-20260423042819..jsonl",
      "updatedAt": "2026-04-23T05:23:34.881Z"
    },
    "wf-20260423-144617": {
      "lastSeq": 6,
      "filePath": "c:\\workspace\\EGPSpace\\output\\runtime\\events\\wf-20260423-144617.jsonl",
      "updatedAt": "2026-04-23T07:17:56.387Z"
    },
    "wf-20260424-000600": {
      "lastSeq": 1,
      "filePath": "c:\\workspace\\EGPSpace\\output\\runtime\\events\\wf-20260424-000600.jsonl",
      "updatedAt": "2026-04-23T16:06:00.432Z"
    },
    "wf-20260424015518": {
      "lastSeq": 1,
      "filePath": "c:\\workspace\\EGPSpace\\output\\runtime\\events\\wf-20260424015518.jsonl",
      "updatedAt": "2026-04-24T01:55:20.418Z"
    },
    "wf-20260424024213.": {
      "lastSeq": 1,
      "filePath": "C:\\workspace\\EGPSpace\\output\\runtime\\events\\wf-20260424024213..jsonl",
      "updatedAt": "2026-04-24T02:42:20.320Z"
    },
    "wf-20260424031346.": {
      "lastSeq": 1,
      "filePath": "C:\\workspace\\EGPSpace\\output\\runtime\\events\\wf-20260424031346..jsonl",
      "updatedAt": "2026-04-24T03:14:12.709Z"
    },
    "wf-20260424033738.": {
      "lastSeq": 1,
      "filePath": "C:\\workspace\\EGPSpace\\output\\runtime\\events\\wf-20260424033738..jsonl",
      "updatedAt": "2026-04-24T03:37:42.891Z"
    },
    "wf-20260424033738": {
      "lastSeq": 1,
      "filePath": "C:\\workspace\\EGPSpace\\output\\runtime\\events\\wf-20260424033738.jsonl",
      "updatedAt": "2026-04-24T03:45:41.264Z"
    },
    "wf-20260424-153619": {
      "lastSeq": 4,
      "filePath": "C:\\workspace\\EGPSpace\\output\\runtime\\events\\wf-20260424-153619.jsonl",
      "updatedAt": "2026-04-24T07:40:13.481Z"
    },
    "wf-20260424074209.": {
      "lastSeq": 10,
      "filePath": "C:\\workspace\\EGPSpace\\output\\runtime\\events\\wf-20260424074209..jsonl",
      "updatedAt": "2026-04-24T08:20:27.416Z"
    },
    "wf-20260424091211.": {
      "lastSeq": 8,
      "filePath": "C:\\workspace\\EGPSpace\\output\\runtime\\events\\wf-20260424091211..jsonl",
      "updatedAt": "2026-04-24T09:52:29.013Z"
    },
    "wf-20260424-181515": {
      "lastSeq": 2,
      "filePath": "C:\\workspace\\EGPSpace\\output\\runtime\\events\\wf-20260424-181515.jsonl",
      "updatedAt": "2026-04-24T10:21:38.391Z"
    },
    "wf-20260424111746.": {
      "lastSeq": 6,
      "filePath": "C:\\workspace\\EGPSpace\\output\\runtime\\events\\wf-20260424111746..jsonl",
      "updatedAt": "2026-04-24T11:53:15.836Z"
    },
    "wf-20260424-203309": {
      "lastSeq": 1,
      "filePath": "C:\\workspace\\EGPSpace\\output\\runtime\\events\\wf-20260424-203309.jsonl",
      "updatedAt": "2026-04-24T12:33:09.591Z"
    },
    "wf-20260424-212932": {
      "lastSeq": 1,
      "filePath": "C:\\workspace\\EGPSpace\\output\\runtime\\events\\wf-20260424-212932.jsonl",
      "updatedAt": "2026-04-24T13:29:32.289Z"
    },
    "wf-20260424-213025": {
      "lastSeq": 1,
      "filePath": "C:\\workspace\\EGPSpace\\output\\runtime\\events\\wf-20260424-213025.jsonl",
      "updatedAt": "2026-04-24T13:30:25.997Z"
    },
    "wf-20260425-013200": {
      "lastSeq": 1,
      "filePath": "C:\\workspace\\EGPSpace\\output\\runtime\\events\\wf-20260425-013200.jsonl",
      "updatedAt": "2026-04-24T17:32:00.532Z"
    },
    "wf-20260425-121659": {
      "lastSeq": 2,
      "filePath": "C:\\workspace\\EGPSpace\\output\\runtime\\events\\wf-20260425-121659.jsonl",
      "updatedAt": "2026-04-25T04:34:18.487Z"
    },
    "wf-20260425-123424": {
      "lastSeq": 2,
      "filePath": "C:\\workspace\\EGPSpace\\output\\runtime\\events\\wf-20260425-123424.jsonl",
      "updatedAt": "2026-04-25T04:38:30.542Z"
    },
    "wf-20260425-142509": {
      "lastSeq": 1,
      "filePath": "C:\\workspace\\EGPSpace\\output\\runtime\\events\\wf-20260425-142509.jsonl",
      "updatedAt": "2026-04-25T06:25:09.356Z"
    },
    "wf-20260425-145548": {
      "lastSeq": 1,
      "filePath": "C:\\workspace\\EGPSpace\\output\\runtime\\events\\wf-20260425-145548.jsonl",
      "updatedAt": "2026-04-25T06:55:49.175Z"
    },
    "wf-20260425-210623": {
      "lastSeq": 1,
      "filePath": "c:\\workspace\\EGPSpace\\output\\runtime\\events\\wf-20260425-210623.jsonl",
      "updatedAt": "2026-04-25T13:06:24.125Z"
    },
    "wf-20260425-213432": {
      "lastSeq": 1,
      "filePath": "c:\\workspace\\EGPSpace\\output\\runtime\\events\\wf-20260425-213432.jsonl",
      "updatedAt": "2026-04-25T13:34:32.665Z"
    },
    "wf-20260425-215748": {
      "lastSeq": 1,
      "filePath": "c:\\workspace\\EGPSpace\\output\\runtime\\events\\wf-20260425-215748.jsonl",
      "updatedAt": "2026-04-25T13:57:48.634Z"
    },
    "wf-20260425-220037": {
      "lastSeq": 1,
      "filePath": "c:\\workspace\\EGPSpace\\output\\runtime\\events\\wf-20260425-220037.jsonl",
      "updatedAt": "2026-04-25T14:00:37.533Z"
    },
    "wf-20260425-220710": {
      "lastSeq": 1,
      "filePath": "c:\\workspace\\EGPSpace\\output\\runtime\\events\\wf-20260425-220710.jsonl",
      "updatedAt": "2026-04-25T14:07:11.056Z"
    },
    "wf-20260425-221658": {
      "lastSeq": 1,
      "filePath": "c:\\workspace\\EGPSpace\\output\\runtime\\events\\wf-20260425-221658.jsonl",
      "updatedAt": "2026-04-25T14:16:59.138Z"
    },
    "wf-20260425-221829": {
      "lastSeq": 1,
      "filePath": "c:\\workspace\\EGPSpace\\output\\runtime\\events\\wf-20260425-221829.jsonl",
      "updatedAt": "2026-04-25T14:18:30.109Z"
    },
    "wf-20260425-225323": {
      "lastSeq": 1,
      "filePath": "C:\\workspace\\EGPSpace\\output\\runtime\\events\\wf-20260425-225323.jsonl",
      "updatedAt": "2026-04-25T14:53:23.698Z"
    },
    "wf-20260425-225506": {
      "lastSeq": 1,
      "filePath": "C:\\workspace\\EGPSpace\\output\\runtime\\events\\wf-20260425-225506.jsonl",
      "updatedAt": "2026-04-25T14:55:06.731Z"
    },
    "wf-20260425-231958": {
      "lastSeq": 1,
      "filePath": "C:\\workspace\\EGPSpace\\output\\runtime\\events\\wf-20260425-231958.jsonl",
      "updatedAt": "2026-04-25T15:19:58.534Z"
    },
    "wf-20260426-001049": {
      "lastSeq": 1,
      "filePath": "C:\\workspace\\EGPSpace\\output\\runtime\\events\\wf-20260426-001049.jsonl",
      "updatedAt": "2026-04-25T16:10:49.854Z"
    },
    "wf-20260426-001145": {
      "lastSeq": 1,
      "filePath": "C:\\workspace\\EGPSpace\\output\\runtime\\events\\wf-20260426-001145.jsonl",
      "updatedAt": "2026-04-25T16:11:45.795Z"
    },
    "wf-20260426-001340": {
      "lastSeq": 1,
      "filePath": "C:\\workspace\\EGPSpace\\output\\runtime\\events\\wf-20260426-001340.jsonl",
      "updatedAt": "2026-04-25T16:13:41.023Z"
    },
    "wf-20260426-001853": {
      "lastSeq": 2,
      "filePath": "C:\\workspace\\EGPSpace\\output\\runtime\\events\\wf-20260426-001853.jsonl",
      "updatedAt": "2026-04-25T16:23:47.935Z"
    },
    "wf-20260426-002550": {
      "lastSeq": 1,
      "filePath": "C:\\workspace\\EGPSpace\\output\\runtime\\events\\wf-20260426-002550.jsonl",
      "updatedAt": "2026-04-25T16:25:50.275Z"
    },
    "wf-20260426-005458": {
      "lastSeq": 2,
      "filePath": "C:\\workspace\\EGPSpace\\output\\runtime\\events\\wf-20260426-005458.jsonl",
      "updatedAt": "2026-04-25T17:01:42.974Z"
    },
    "wf-20260426-010205": {
      "lastSeq": 2,
      "filePath": "C:\\workspace\\EGPSpace\\output\\runtime\\events\\wf-20260426-010205.jsonl",
      "updatedAt": "2026-04-25T17:07:44.612Z"
    },
    "wf-20260426-011701": {
      "lastSeq": 2,
      "filePath": "C:\\workspace\\EGPSpace\\output\\runtime\\events\\wf-20260426-011701.jsonl",
      "updatedAt": "2026-04-25T17:28:15.100Z"
    },
    "wf-20260426-012830": {
      "lastSeq": 1,
      "filePath": "C:\\workspace\\EGPSpace\\output\\runtime\\events\\wf-20260426-012830.jsonl",
      "updatedAt": "2026-04-25T17:28:30.230Z"
    },
    "wf-20260426-113915": {
      "lastSeq": 1,
      "filePath": "C:\\workspace\\EGPSpace\\output\\runtime\\events\\wf-20260426-113915.jsonl",
      "updatedAt": "2026-04-26T03:39:15.208Z"
    },
    "wf-20260426-201003": {
      "lastSeq": 1,
      "filePath": "C:\\workspace\\EGPSpace\\output\\runtime\\events\\wf-20260426-201003.jsonl",
      "updatedAt": "2026-04-26T12:10:04.207Z"
    },
    "wf-20260426-203414": {
      "lastSeq": 1,
      "filePath": "C:\\workspace\\EGPSpace\\output\\runtime\\events\\wf-20260426-203414.jsonl",
      "updatedAt": "2026-04-26T12:34:14.890Z"
    },
    "wf-20260426-203558": {
      "lastSeq": 3,
      "filePath": "C:\\workspace\\EGPSpace\\output\\runtime\\events\\wf-20260426-203558.jsonl",
      "updatedAt": "2026-04-26T12:36:32.745Z"
    },
    "wf-20260426-210442": {
      "lastSeq": 1,
      "filePath": "C:\\workspace\\EGPSpace\\output\\runtime\\events\\wf-20260426-210442.jsonl",
      "updatedAt": "2026-04-26T13:04:43.001Z"
    },
    "wf-20260426-210808": {
      "lastSeq": 1,
      "filePath": "C:\\workspace\\EGPSpace\\output\\runtime\\events\\wf-20260426-210808.jsonl",
      "updatedAt": "2026-04-26T13:08:08.892Z"
    },
    "wf-20260426-210950": {
      "lastSeq": 1,
      "filePath": "C:\\workspace\\EGPSpace\\output\\runtime\\events\\wf-20260426-210950.jsonl",
      "updatedAt": "2026-04-26T13:09:50.824Z"
    },
    "wf-20260426-215001": {
      "lastSeq": 1,
      "filePath": "C:\\workspace\\EGPSpace\\output\\runtime\\events\\wf-20260426-215001.jsonl",
      "updatedAt": "2026-04-26T13:50:01.220Z"
    },
    "wf-20260426-224142": {
      "lastSeq": 1,
      "filePath": "C:\\workspace\\EGPSpace\\output\\runtime\\events\\wf-20260426-224142.jsonl",
      "updatedAt": "2026-04-26T14:41:42.602Z"
    },
    "wf-20260426-224335": {
      "lastSeq": 1,
      "filePath": "C:\\workspace\\EGPSpace\\output\\runtime\\events\\wf-20260426-224335.jsonl",
      "updatedAt": "2026-04-26T14:43:36.205Z"
    },
    "wf-20260426-225458": {
      "lastSeq": 1,
      "filePath": "C:\\workspace\\EGPSpace\\output\\runtime\\events\\wf-20260426-225458.jsonl",
      "updatedAt": "2026-04-26T14:54:59.188Z"
    },
    "wf-20260428-105240": {
      "lastSeq": 1,
      "filePath": "C:\\workspace\\EGPSpace\\output\\runtime\\events\\wf-20260428-105240.jsonl",
      "updatedAt": "2026-04-28T02:52:40.513Z"
    },
    "wf-20260428-105545": {
      "lastSeq": 1,
      "filePath": "C:\\workspace\\EGPSpace\\output\\runtime\\events\\wf-20260428-105545.jsonl",
      "updatedAt": "2026-04-28T02:55:45.817Z"
    },
    "wf-20260428-105850": {
      "lastSeq": 1,
      "filePath": "C:\\workspace\\EGPSpace\\output\\runtime\\events\\wf-20260428-105850.jsonl",
      "updatedAt": "2026-04-28T02:58:50.296Z"
    },
    "egpspace-componentization-20260428113000": {
      "lastSeq": 2,
      "filePath": "C:\\workspace\\EGPSpace\\output\\runtime\\events\\egpspace-componentization-20260428113000.jsonl",
      "updatedAt": "2026-04-28T03:44:56.374Z"
    },
    "wf-20260428-115027": {
      "lastSeq": 3,
      "filePath": "C:\\workspace\\EGPSpace\\output\\runtime\\events\\wf-20260428-115027.jsonl",
      "updatedAt": "2026-04-28T05:06:04.276Z"
    },
    "wf-20260428-131250": {
      "lastSeq": 2,
      "filePath": "C:\\workspace\\EGPSpace\\output\\runtime\\events\\wf-20260428-131250.jsonl",
      "updatedAt": "2026-04-28T05:12:58.744Z"
    },
    "wf-20260428-143637": {
      "lastSeq": 1,
      "filePath": "C:\\workspace\\EGPSpace\\output\\runtime\\events\\wf-20260428-143637.jsonl",
      "updatedAt": "2026-04-28T06:36:38.056Z"
    },
    "wf-20260428-capability-atomization": {
      "lastSeq": 3,
      "filePath": "C:\\workspace\\EGPSpace\\output\\runtime\\events\\wf-20260428-capability-atomization.jsonl",
      "updatedAt": "2026-04-28T06:49:43.062Z"
    },
    "wf-20260428-154641": {
      "lastSeq": 6,
      "filePath": "C:\\workspace\\EGPSpace\\output\\runtime\\events\\wf-20260428-154641.jsonl",
      "updatedAt": "2026-04-28T08:05:32.074Z"
    },
    "wf-20260428083531.": {
      "lastSeq": 14,
      "filePath": "C:\\workspace\\EGPSpace\\output\\runtime\\events\\wf-20260428083531..jsonl",
      "updatedAt": "2026-04-28T10:20:37.445Z"
    },
    "wf-20260428105932.": {
      "lastSeq": 14,
      "filePath": "C:\\workspace\\EGPSpace\\output\\runtime\\events\\wf-20260428105932..jsonl",
      "updatedAt": "2026-04-28T11:52:53.580Z"
    },
    "wf-20260428120154.": {
      "lastSeq": 14,
      "filePath": "C:\\workspace\\EGPSpace\\output\\runtime\\events\\wf-20260428120154..jsonl",
      "updatedAt": "2026-04-28T13:13:50.615Z"
    },
    "wf-20260428140545.": {
      "lastSeq": 14,
      "filePath": "C:\\workspace\\EGPSpace\\output\\runtime\\events\\wf-20260428140545..jsonl",
      "updatedAt": "2026-04-28T15:26:09.271Z"
    },
    "wf-20260428153150.": {
      "lastSeq": 14,
      "filePath": "C:\\workspace\\EGPSpace\\output\\runtime\\events\\wf-20260428153150..jsonl",
      "updatedAt": "2026-04-28T17:34:03.051Z"
    },
    "wf-20260428234611.": {
      "lastSeq": 14,
      "filePath": "C:\\workspace\\EGPSpace\\output\\runtime\\events\\wf-20260428234611..jsonl",
      "updatedAt": "2026-04-29T00:24:51.754Z"
    },
    "wf-20260429021559.": {
      "lastSeq": 14,
      "filePath": "C:\\workspace\\EGPSpace\\output\\runtime\\events\\wf-20260429021559..jsonl",
      "updatedAt": "2026-04-29T03:41:55.326Z"
    },
    "wf-20260429045944.": {
      "lastSeq": 14,
      "filePath": "C:\\workspace\\EGPSpace\\output\\runtime\\events\\wf-20260429045944..jsonl",
      "updatedAt": "2026-04-29T05:40:23.290Z"
    },
    "wf-20260429054300.": {
      "lastSeq": 14,
      "filePath": "C:\\workspace\\EGPSpace\\output\\runtime\\events\\wf-20260429054300..jsonl",
      "updatedAt": "2026-04-29T11:28:57.655Z"
    },
    "wf-20260429132738.": {
      "lastSeq": 14,
      "filePath": "C:\\workspace\\EGPSpace\\output\\runtime\\events\\wf-20260429132738..jsonl",
      "updatedAt": "2026-04-29T15:41:30.053Z"
    },
    "wf-20260430013937.": {
      "lastSeq": 14,
      "filePath": "C:\\workspace\\EGPSpace\\output\\runtime\\events\\wf-20260430013937..jsonl",
      "updatedAt": "2026-04-30T02:57:13.579Z"
    },
    "wf-20260430034429.": {
      "lastSeq": 1,
      "filePath": "C:\\workspace\\EGPSpace\\output\\runtime\\events\\wf-20260430034429..jsonl",
      "updatedAt": "2026-04-30T03:48:10.603Z"
    },
    "wf-20260430-120735": {
      "lastSeq": 10,
      "filePath": "C:\\workspace\\EGPSpace\\output\\runtime\\events\\wf-20260430-120735.jsonl",
      "updatedAt": "2026-04-30T04:23:51.265Z"
    },
    "wf-20260430-122900": {
      "lastSeq": 3,
      "filePath": "C:\\workspace\\EGPSpace\\output\\runtime\\events\\wf-20260430-122900.jsonl",
      "updatedAt": "2026-04-30T04:54:11.208Z"
    },
    "wf-20260430-130629": {
      "lastSeq": 6,
      "filePath": "C:\\workspace\\EGPSpace\\output\\runtime\\events\\wf-20260430-130629.jsonl",
      "updatedAt": "2026-04-30T05:08:34.139Z"
    },
    "wf-20260430-150500": {
      "lastSeq": 10,
      "filePath": "C:\\workspace\\EGPSpace\\output\\runtime\\events\\wf-20260430-150500.jsonl",
      "updatedAt": "2026-04-30T07:24:14.441Z"
    },
    "wf-20260430-170116": {
      "lastSeq": 1,
      "filePath": "C:\\workspace\\EGPSpace\\output\\runtime\\events\\wf-20260430-170116.jsonl",
      "updatedAt": "2026-04-30T09:01:16.684Z"
    },
    "wf-20260430-170529": {
      "lastSeq": 1,
      "filePath": "C:\\workspace\\EGPSpace\\output\\runtime\\events\\wf-20260430-170529.jsonl",
      "updatedAt": "2026-04-30T09:05:29.579Z"
    },
    "wf-20260430-170530": {
      "lastSeq": 1,
      "filePath": "C:\\workspace\\EGPSpace\\output\\runtime\\events\\wf-20260430-170530.jsonl",
      "updatedAt": "2026-04-30T09:05:30.439Z"
    },
    "wf-20260430-170540": {
      "lastSeq": 1,
      "filePath": "C:\\workspace\\EGPSpace\\output\\runtime\\events\\wf-20260430-170540.jsonl",
      "updatedAt": "2026-04-30T09:05:41.012Z"
    },
    "wf-20260430092548.": {
      "lastSeq": 7,
      "filePath": "C:\\workspace\\EGPSpace\\output\\runtime\\events\\wf-20260430092548..jsonl",
      "updatedAt": "2026-04-30T09:51:27.462Z"
    },
    "wf-20260430095336.": {
      "lastSeq": 14,
      "filePath": "C:\\workspace\\EGPSpace\\output\\runtime\\events\\wf-20260430095336..jsonl",
      "updatedAt": "2026-04-30T10:01:52.879Z"
    },
    "wf-20260430101628.": {
      "lastSeq": 15,
      "filePath": "C:\\workspace\\EGPSpace\\output\\runtime\\events\\wf-20260430101628..jsonl",
      "updatedAt": "2026-04-30T10:23:26.197Z"
    },
    "wf-20260430141647.": {
      "lastSeq": 14,
      "filePath": "C:\\workspace\\EGPSpace\\output\\runtime\\events\\wf-20260430141647..jsonl",
      "updatedAt": "2026-04-30T14:35:59.232Z"
    },
    "wf-20260430143735.": {
      "lastSeq": 17,
      "filePath": "C:\\workspace\\EGPSpace\\output\\runtime\\events\\wf-20260430143735..jsonl",
      "updatedAt": "2026-04-30T15:01:41.678Z"
    },
    "wf-20260430152415.": {
      "lastSeq": 14,
      "filePath": "C:\\workspace\\EGPSpace\\output\\runtime\\events\\wf-20260430152415..jsonl",
      "updatedAt": "2026-04-30T15:30:18.194Z"
    },
    "wf-20260430154942.": {
      "lastSeq": 9,
      "filePath": "C:\\workspace\\EGPSpace\\output\\runtime\\events\\wf-20260430154942..jsonl",
      "updatedAt": "2026-04-30T16:03:46.032Z"
    },
    "wf-20260430160932.": {
      "lastSeq": 17,
      "filePath": "C:\\workspace\\EGPSpace\\output\\runtime\\events\\wf-20260430160932..jsonl",
      "updatedAt": "2026-04-30T16:33:13.386Z"
    },
    "wf-20260430164236.": {
      "lastSeq": 14,
      "filePath": "C:\\workspace\\EGPSpace\\output\\runtime\\events\\wf-20260430164236..jsonl",
      "updatedAt": "2026-04-30T17:44:02.120Z"
    },
    "wf-20260501014700": {
      "lastSeq": 16,
      "filePath": "C:\\workspace\\EGPSpace\\output\\runtime\\events\\wf-20260501014700.jsonl",
      "updatedAt": "2026-04-30T18:15:12.759Z"
    },
    "wf-20260501082000": {
      "lastSeq": 15,
      "filePath": "C:\\workspace\\EGPSpace\\output\\runtime\\events\\wf-20260501082000.jsonl",
      "updatedAt": "2026-05-01T00:34:46.542Z"
    },
    "wf-20260501010003.": {
      "lastSeq": 18,
      "filePath": "C:\\workspace\\EGPSpace\\output\\runtime\\events\\wf-20260501010003..jsonl",
      "updatedAt": "2026-05-01T01:12:07.323Z"
    },
    "wf-20260501-093134": {
      "lastSeq": 2,
      "filePath": "C:\\workspace\\EGPSpace\\output\\runtime\\events\\wf-20260501-093134.jsonl",
      "updatedAt": "2026-05-01T01:38:46.361Z"
    },
    "wf-20260501-094517": {
      "lastSeq": 2,
      "filePath": "C:\\workspace\\EGPSpace\\output\\runtime\\events\\wf-20260501-094517.jsonl",
      "updatedAt": "2026-05-01T01:50:19.926Z"
    },
    "wf-20260501-095845": {
      "lastSeq": 2,
      "filePath": "C:\\workspace\\EGPSpace\\output\\runtime\\events\\wf-20260501-095845.jsonl",
      "updatedAt": "2026-05-01T02:06:22.093Z"
    },
    "wf-20260501-101425": {
      "lastSeq": 2,
      "filePath": "C:\\workspace\\EGPSpace\\output\\runtime\\events\\wf-20260501-101425.jsonl",
      "updatedAt": "2026-05-01T02:24:44.809Z"
    },
    "wf-20260502173200": {
      "lastSeq": 16,
      "filePath": "C:\\workspace\\EGPSpace\\output\\runtime\\events\\wf-20260502173200.jsonl",
      "updatedAt": "2026-05-02T10:03:09.344Z"
    },
    "wf-20260502101426.": {
      "lastSeq": 6,
      "filePath": "C:\\workspace\\EGPSpace\\output\\runtime\\events\\wf-20260502101426..jsonl",
      "updatedAt": "2026-05-02T10:16:38.484Z"
    },
    "wf-20260502102344.": {
      "lastSeq": 6,
      "filePath": "C:\\workspace\\EGPSpace\\output\\runtime\\events\\wf-20260502102344..jsonl",
      "updatedAt": "2026-05-02T10:29:13.171Z"
    },
    "wf-20260502122410.": {
      "lastSeq": 14,
      "filePath": "C:\\workspace\\EGPSpace\\output\\runtime\\events\\wf-20260502122410..jsonl",
      "updatedAt": "2026-05-02T12:33:35.587Z"
    },
    "wf-20260502-204815": {
      "lastSeq": 1,
      "filePath": "C:\\workspace\\EGPSpace\\output\\runtime\\events\\wf-20260502-204815.jsonl",
      "updatedAt": "2026-05-02T12:48:15.500Z"
    },
    "wf-20260502-212821": {
      "lastSeq": 1,
      "filePath": "C:\\workspace\\EGPSpace\\output\\runtime\\events\\wf-20260502-212821.jsonl",
      "updatedAt": "2026-05-02T13:28:22.061Z"
    },
    "wf-20260502-213159": {
      "lastSeq": 1,
      "filePath": "C:\\workspace\\EGPSpace\\output\\runtime\\events\\wf-20260502-213159.jsonl",
      "updatedAt": "2026-05-02T13:31:59.993Z"
    },
    "wf-20260502-221721": {
      "lastSeq": 1,
      "filePath": "C:\\workspace\\EGPSpace\\output\\runtime\\events\\wf-20260502-221721.jsonl",
      "updatedAt": "2026-05-02T14:17:21.593Z"
    },
    "wf-20260502-230106": {
      "lastSeq": 1,
      "filePath": "C:\\workspace\\EGPSpace\\output\\runtime\\events\\wf-20260502-230106.jsonl",
      "updatedAt": "2026-05-02T15:01:06.745Z"
    },
    "wf-20260502-231512": {
      "lastSeq": 1,
      "filePath": "C:\\workspace\\EGPSpace\\output\\runtime\\events\\wf-20260502-231512.jsonl",
      "updatedAt": "2026-05-02T15:15:12.789Z"
    },
    "wf-20260502-231820": {
      "lastSeq": 1,
      "filePath": "C:\\workspace\\EGPSpace\\output\\runtime\\events\\wf-20260502-231820.jsonl",
      "updatedAt": "2026-05-02T15:18:21.055Z"
    },
    "wf-20260502-232705": {
      "lastSeq": 1,
      "filePath": "C:\\workspace\\EGPSpace\\output\\runtime\\events\\wf-20260502-232705.jsonl",
      "updatedAt": "2026-05-02T15:27:06.026Z"
    },
    "wf-20260502-233540": {
      "lastSeq": 1,
      "filePath": "C:\\workspace\\EGPSpace\\output\\runtime\\events\\wf-20260502-233540.jsonl",
      "updatedAt": "2026-05-02T15:35:40.319Z"
    },
    "wf-20260502-234945": {
      "lastSeq": 1,
      "filePath": "C:\\workspace\\EGPSpace\\output\\runtime\\events\\wf-20260502-234945.jsonl",
      "updatedAt": "2026-05-02T15:49:45.898Z"
    },
    "wf-20260502-235319": {
      "lastSeq": 1,
      "filePath": "C:\\workspace\\EGPSpace\\output\\runtime\\events\\wf-20260502-235319.jsonl",
      "updatedAt": "2026-05-02T15:53:19.498Z"
    },
    "wf-20260503-090300": {
      "lastSeq": 1,
      "filePath": "C:\\workspace\\EGPSpace\\output\\runtime\\events\\wf-20260503-090300.jsonl",
      "updatedAt": "2026-05-03T01:03:00.363Z"
    },
    "wf-20260503011729.": {
      "lastSeq": 15,
      "filePath": "C:\\workspace\\EGPSpace\\output\\runtime\\events\\wf-20260503011729..jsonl",
      "updatedAt": "2026-05-03T01:23:30.994Z"
    },
    "wf-20260503-092220": {
      "lastSeq": 1,
      "filePath": "C:\\workspace\\EGPSpace\\output\\runtime\\events\\wf-20260503-092220.jsonl",
      "updatedAt": "2026-05-03T01:22:21.197Z"
    },
    "wf-20260503-093302": {
      "lastSeq": 1,
      "filePath": "C:\\workspace\\EGPSpace\\output\\runtime\\events\\wf-20260503-093302.jsonl",
      "updatedAt": "2026-05-03T01:33:02.722Z"
    },
    "wf-202605030940": {
      "lastSeq": 16,
      "filePath": "C:\\workspace\\EGPSpace\\output\\runtime\\events\\wf-202605030940.jsonl",
      "updatedAt": "2026-05-03T01:48:48.344Z"
    },
    "wf-20260503-094912": {
      "lastSeq": 1,
      "filePath": "C:\\workspace\\EGPSpace\\output\\runtime\\events\\wf-20260503-094912.jsonl",
      "updatedAt": "2026-05-03T01:49:12.439Z"
    },
    "wf-202605031017": {
      "lastSeq": 1,
      "filePath": "C:\\workspace\\EGPSpace\\output\\runtime\\events\\wf-202605031017.jsonl",
      "updatedAt": "2026-05-03T02:18:11.073Z"
    }
  }
}